tests/__init__.py
tests/tools/__init__.py
tests/tools/test_ElementProperties.py
tests/tools/test_FitGaussianFunction.py
tests/tools/test_FitPolynomialFunction.py
tests/tools/test_XRayDataWinxray.py
tests/tools/test_XRayTransitionData.py
tests/tools/test_fitTools.py
tests/ui/__init__.py
tests/ui/console/__init__.py
tests/ui/console/test_SpectrumAnalyzer.py
tests/ui/console/test_XrayLineReferenceManager.py
xrayspectrumanalyzer/__init__.py
xrayspectrumanalyzer/tools/ElementProperties.py
xrayspectrumanalyzer/tools/FitGaussianFunction.py
xrayspectrumanalyzer/tools/FitPolynomialFunction.py
xrayspectrumanalyzer/tools/XRayDataWinxray.py
xrayspectrumanalyzer/tools/XRayTransitionData.py
xrayspectrumanalyzer/tools/__init__.py
xrayspectrumanalyzer/tools/fitTools.py
xrayspectrumanalyzer/ui/__init__.py
xrayspectrumanalyzer/ui/console/SpectrumAnalyzer.py
xrayspectrumanalyzer/ui/console/XrayLineReferenceManager.py
xrayspectrumanalyzer/ui/console/__init__.py
xrayspectrumanalyzer-0.2.dist-info/DESCRIPTION.rst
xrayspectrumanalyzer-0.2.dist-info/METADATA
xrayspectrumanalyzer-0.2.dist-info/RECORD
xrayspectrumanalyzer-0.2.dist-info/WHEEL
xrayspectrumanalyzer-0.2.dist-info/metadata.json
xrayspectrumanalyzer-0.2.dist-info/top_level.txt
