Metadata-Version: 2.0
Name: xrayspectrumanalyzer
Version: 0.2
Summary: Extract peak intensity from EDS spectrum obtained with a EM.
Home-page: UNKNOWN
Author: Hendrix Demers
Author-email: hendrix.demers@mail.mcgill.ca
License: Apache License, Version 2.0
Platform: UNKNOWN
Classifier: Development Status :: 4 - Beta
Classifier: Environment :: Console
Classifier: Intended Audience :: Developers
Classifier: Intended Audience :: Science/Research
Classifier: License :: OSI Approved :: Apache Software License
Classifier: Natural Language :: English
Classifier: Programming Language :: Python
Classifier: Operating System :: OS Independent
Classifier: Topic :: Scientific/Engineering
Requires-Dist: numpy
Requires-Dist: scipy
Requires-Dist: matplotlib
Requires-Dist: Pillow
Requires-Dist: six
Requires-Dist: lmfit
